Metadata-Version: 1.0
Name: mytestlib-kitamaru
Version: 1.0.0
Summary: My Test Library.
Home-page: UNKNOWN
Author: Kitamaru
Author-email: kz_hiei5968@ybb.ne.jp
License: UNKNOWN
Platform: UNKNOWN
